LICENSE
README.rst
setup.py
deepti_utils/__init__.py
deepti_utils/plotting.py
deepti_utils.egg-info/PKG-INFO
deepti_utils.egg-info/SOURCES.txt
deepti_utils.egg-info/dependency_links.txt
deepti_utils.egg-info/requires.txt
deepti_utils.egg-info/top_level.txt